biocmd/__init__.py
biocmd/bio_data.py
biocmd/bio_env.py
biocmd/bio_script.py
biocmd/bio_task.py
biocmd/entry.py
biocmd/job.py
biocmd/job2.py
biocmd/local_config.py
biocmd/pipeline.py
biocmd/request.py
biocmd/server_config.py
biocmd/task.py
biocmd-0.1.1.dist-info/LICENSE
biocmd-0.1.1.dist-info/METADATA
biocmd-0.1.1.dist-info/WHEEL
biocmd-0.1.1.dist-info/entry_points.txt
biocmd-0.1.1.dist-info/top_level.txt
biocmd-0.1.1.dist-info/RECORD
