Metadata-Version: 2.1
Name: biocmd
Version: 0.1.1
Summary: BioLab Client
Home-page: https://github.com/BioHubX/biocmd
Author: Yaping-Liu
Author-email: applesline@163.com
License: Apache License 2.0
Platform: UNKNOWN
Requires-Dist: click
